geometry/__init__.py
geometry/angles.py
geometry/base.py
geometry/checks.py
geometry/coordinate_frame.py
geometry/gps.py
geometry/mass.py
geometry/point.py
geometry/py.typed
geometry/quaternion.py
geometry/time.py
geometry/transformation.py
geometry/utils.py
pfc_geometry-0.2.20.dist-info/METADATA
pfc_geometry-0.2.20.dist-info/WHEEL
pfc_geometry-0.2.20.dist-info/licenses/LICENSE
pfc_geometry-0.2.20.dist-info/RECORD
