Metadata-Version: 2.4
Name: pfc-geometry
Version: 0.2.20
Summary: A library for working with 3D geometry.
License-File: LICENSE
Requires-Python: >=3.12
Requires-Dist: numpy-quaternion>=2024.0.7
Requires-Dist: numpy>=2.1.3
Requires-Dist: pandas>=2.2.3
Requires-Dist: rowan>=1.3.2
